{
  "configVersion": 1,
  "timestamp": 1754851926589,
  "index": "/index.html",
  "assetGroups": [
    {
      "name": "app",
      "installMode": "prefetch",
      "updateMode": "prefetch",
      "cacheQueryOptions": {
        "ignoreVary": true
      },
      "urls": [
        "/favicon.ico",
        "/index.html",
        "/main-C2CIM5LN.js",
        "/manifest.webmanifest",
        "/polyfills-B6TNHZQ6.js",
        "/styles-EDAKTOV6.css"
      ],
      "patterns": []
    },
    {
      "name": "assets",
      "installMode": "lazy",
      "updateMode": "prefetch",
      "cacheQueryOptions": {
        "ignoreVary": true
      },
      "urls": [
        "/icons/appsymbol-1024.png",
        "/icons/appsymbol-192.png",
        "/icons/appsymbol-512.png",
        "/icons/icon-128x128.png",
        "/icons/icon-144x144.png",
        "/icons/icon-152x152.png",
        "/icons/icon-192x192.png",
        "/icons/icon-384x384.png",
        "/icons/icon-512x512.png",
        "/icons/icon-72x72.png",
        "/icons/icon-96x96.png"
      ],
      "patterns": []
    }
  ],
  "dataGroups": [],
  "hashTable": {
    "/favicon.ico": "9c39f434fe1261f68c5e3eefdf734630d99c5670",
    "/icons/appsymbol-1024.png": "43dbb1ebfe98805dee6386b5c356ed000df6eecf",
    "/icons/appsymbol-192.png": "416a8bd7d89906bafa3553f20c115c7aad0a8e7a",
    "/icons/appsymbol-512.png": "40e5121a088ce0fe5ef9e155ca49bd5ce1bd3dc9",
    "/icons/icon-128x128.png": "f912963bdc6d5a38d8f1dd0afbaab2ce8d657acb",
    "/icons/icon-144x144.png": "b155fd5f2fd5d2ea7760721063003c4cd95fd783",
    "/icons/icon-152x152.png": "eae6e0f0c8afb8aaae339e2a569b43e9238e5e6c",
    "/icons/icon-192x192.png": "15c4180454633880d98674aa7394656196c91584",
    "/icons/icon-384x384.png": "94a915751ef6c9282df9aea405ad679230631814",
    "/icons/icon-512x512.png": "1de182f76f7329dfa8f9fcdd1fdcdd695bea6a99",
    "/icons/icon-72x72.png": "aa88a6096bd973be7f6d7a5489bfa6bc2463f8c4",
    "/icons/icon-96x96.png": "7fb8f59c30ce2ff12c700321a0b39e14b3dc8f95",
    "/index.html": "8a4abc6f529e3f7864e3d21b98fa83d00258269a",
    "/main-C2CIM5LN.js": "39a64dfe2170106ad90e240f052d25250c19eaeb",
    "/manifest.webmanifest": "60a918b837ef2f57f1ddc6a83654e223310b6b1a",
    "/polyfills-B6TNHZQ6.js": "bf76ac291d7f51c1139b7edcf86b359a30c08c64",
    "/styles-EDAKTOV6.css": "d9c21f9a61443fee890da7a5d6056f74511c6948"
  },
  "navigationUrls": [
    {
      "positive": true,
      "regex": "^\\/.*$"
    },
    {
      "positive": false,
      "regex": "^\\/(?:.+\\/)?[^/]*\\.[^/]*$"
    },
    {
      "positive": false,
      "regex": "^\\/(?:.+\\/)?[^/]*__[^/]*$"
    },
    {
      "positive": false,
      "regex": "^\\/(?:.+\\/)?[^/]*__[^/]*\\/.*$"
    }
  ],
  "navigationRequestStrategy": "performance"
}